sinzutils/__init__.py
sinzutils/constraints.py
sinzutils/distributions.py
sinzutils/measures.py
sinzutils/regularizers.py
sinzutils/training.py
sinzutils/utils.py
sinzutils/data/__init__.py
sinzutils/data/datasets.py
sinzutils/data/exceptions.py
sinzutils/data/samplers.py
sinzutils/data/transforms.py
sinzutils/data/utils.py
sinzutils/layers/__init__.py
sinzutils/layers/activations.py
sinzutils/layers/attention.py
sinzutils/layers/cores.py
sinzutils/layers/flows.py
sinzutils/layers/hermite_layers.py
sinzutils/layers/legacy.py
sinzutils/layers/readouts.py
sinzident-0.0.0rc1.dist-info/LICENSE
sinzident-0.0.0rc1.dist-info/METADATA
sinzident-0.0.0rc1.dist-info/WHEEL
sinzident-0.0.0rc1.dist-info/top_level.txt
sinzident-0.0.0rc1.dist-info/RECORD
