Metadata-Version: 2.1
Name: sinzident
Version: 0.0.0rc1
Summary: Sinz Lab Neural System Identification Utilities
Home-page: https://github.com/sinzlab/sinzident
Author: Sinz Lab
Author-email: software@sinzlab.net
License: UNKNOWN
Platform: UNKNOWN
Requires-Dist: numpy
Requires-Dist: torch
Requires-Dist: tqdm
Requires-Dist: pandas
Requires-Dist: h5py
